iotagents/__init__.py
iotagents/main.py
iotagents-0.0.1.dist-info/LICENSE
iotagents-0.0.1.dist-info/METADATA
iotagents-0.0.1.dist-info/WHEEL
iotagents-0.0.1.dist-info/RECORD
